admin_totals/__init__.py
admin_totals/admin.py
admin_totals/templates/admin_totals/change_list_results_totals.html
admin_totals/templates/admin_totals/change_list_totals.html
admin_totals/templatetags/__init__.py
admin_totals/templatetags/admin_totals.py
tests/__init__.py
tests/settings.py
tests/urls.py
tests/admin_changelist/__init__.py
tests/admin_changelist/admin.py
tests/admin_changelist/models.py
tests/admin_changelist/tests.py
tests/admin_changelist/urls.py
admin_totals-1.0.1.dist-info/LICENSE_GPL2.0.txt
admin_totals-1.0.1.dist-info/LICENSE_LGPL_2.1.txt
admin_totals-1.0.1.dist-info/METADATA
admin_totals-1.0.1.dist-info/WHEEL
admin_totals-1.0.1.dist-info/top_level.txt
admin_totals-1.0.1.dist-info/RECORD
