Metadata-Version: 2.1
Name: admin-totals
Version: 1.0.1
Summary: Django Admin Totals, add totals to your columns in Django admin.    
Home-page: https://github.com/douwevandermeij/admin-totals
Author: Douwe van der Meij
Author-email: douwe@karibu-online.nl
License: UNKNOWN
Platform: UNKNOWN
Classifier: Development Status :: 5 - Production/Stable
Classifier: Environment :: Web Environment
Classifier: Intended Audience :: Developers
Classifier: License :: OSI Approved :: GNU General Public License v2 (GPLv2)
Classifier: License :: OSI Approved :: GNU Lesser General Public License v2 or later (LGPLv2+)
Classifier: Operating System :: OS Independent
Classifier: Programming Language :: Python
Classifier: Framework :: Django
Requires-Dist: Django
